chatgptfree/__init__.py
chatgptfree/chatgptfree.py
tests/__init__.py
tests/test_myfunctions.py
chatgptfree-0.4.0.dist-info/METADATA
chatgptfree-0.4.0.dist-info/WHEEL
chatgptfree-0.4.0.dist-info/top_level.txt
chatgptfree-0.4.0.dist-info/RECORD
