Metadata-Version: 2.1
Name: chatgptfree
Version: 0.4.0
Summary: Bot to prompt ChatGPT like the API but free.
Author: Dinis Valente
